version_demo/__init__.py
version_demo/akg.py
version_dem-0.0.4.dist-info/METADATA
version_dem-0.0.4.dist-info/WHEEL
version_dem-0.0.4.dist-info/top_level.txt
version_dem-0.0.4.dist-info/RECORD
