Metadata-Version: 2.1
Name: version-dem
Version: 0.0.4
Summary: Just demo for checking how is version work
Home-page: https://github.com/paytm/paytm-pg-python-sdk
Author: avneesh gupta
Author-email: avneesh.gupta@paytm.com
License: UNKNOWN
Platform: UNKNOWN
Classifier: Programming Language :: Python :: 3
Classifier: Operating System :: OS Independent
